src/__init__.py
src/main.py
src/main_http.py
src/api/__init__.py
src/api/mcp_server.py
src/api/mock_data.py
src/api/models.py
src/api/query_processor.py
src/config/__init__.py
src/config/settings.py
mcp_stock_screener-1.0.3.dist-info/METADATA
mcp_stock_screener-1.0.3.dist-info/WHEEL
mcp_stock_screener-1.0.3.dist-info/entry_points.txt
mcp_stock_screener-1.0.3.dist-info/licenses/LICENSE
mcp_stock_screener-1.0.3.dist-info/RECORD
