Metadata-Version: 2.4
Name: mcp-stock-screener
Version: 1.0.3
Summary: AI-powered financial analysis system that processes natural language queries and returns structured stock analysis results via MCP
License-File: LICENSE
Requires-Python: >=3.10
Requires-Dist: aiohttp>=3.12.14
Requires-Dist: fastapi>=0.100.0
Requires-Dist: httpx>=0.24.0
Requires-Dist: mcp>=1.12.1
Requires-Dist: numpy>=1.24.0
Requires-Dist: pandas>=2.0.0
Requires-Dist: pydantic-settings>=2.0.0
Requires-Dist: pydantic>=2.0.0
Requires-Dist: questdb>=3.0.0
Requires-Dist: redis>=4.5.0
Requires-Dist: scikit-learn>=1.3.0
Requires-Dist: starlette>=0.27.0
Requires-Dist: uvicorn>=0.23.0
Requires-Dist: xgboost>=2.0.0
Provides-Extra: dev
Requires-Dist: black>=23.0.0; extra == 'dev'
Requires-Dist: mypy>=1.5.0; extra == 'dev'
Requires-Dist: pytest-asyncio>=0.21.0; extra == 'dev'
Requires-Dist: pytest-cov>=4.0.0; extra == 'dev'
Requires-Dist: pytest>=7.0.0; extra == 'dev'
Requires-Dist: ruff>=0.1.0; extra == 'dev'
